structurelib/__init__.py
structurelib/_identifier.py
structurelib/_structure.py
structurelib/types.py
structurelib/_dumping/__init__.py
structurelib/_dumping/_dumpers.py
structurelib/_dumping/_dumps.py
structurelib-0.1.0.dist-info/LICENSE
structurelib-0.1.0.dist-info/METADATA
structurelib-0.1.0.dist-info/WHEEL
structurelib-0.1.0.dist-info/top_level.txt
structurelib-0.1.0.dist-info/RECORD
