Metadata-Version: 2.1
Name: structurelib
Version: 0.1.0
Summary: similar function to the builtin struct-library but more friendly
Home-page: https://github.com/PlayerG9/structlib-py/
Author: PlayerG9
License: MIT
Project-URL: Author Github, https://github.com/PlayerG9
Project-URL: Homepage, https://github.com/PlayerG9/structlib-py/
Project-URL: Bug Tracker, https://github.com/PlayerG9/structlib-py/issues
Classifier: Intended Audience :: Developers
Classifier: Intended Audience :: System Administrators
Classifier: License :: OSI Approved :: MIT License
Classifier: Natural Language :: English
Classifier: Operating System :: OS Independent
Classifier: Programming Language :: Python :: 3
Classifier: Programming Language :: Python :: 3 :: Only
Classifier: Programming Language :: Python :: 3.7
Classifier: Programming Language :: Python :: 3.8
Classifier: Programming Language :: Python :: 3.9
Classifier: Programming Language :: Python :: 3.10
Classifier: Programming Language :: Python :: 3.11
Classifier: Programming Language :: Python :: 3.12
Classifier: Programming Language :: Python :: 3.13
Classifier: Topic :: Utilities
License-File: LICENSE
